<?xml version="1.0" encoding="UTF-8" standalone="yes"?>
<node artifactManager="be.nabu.eai.module.types.structure.StructureManager" created="2022-11-16T11:11:58.300+01:00" lastModified="2022-11-17T12:04:15.986+01:00" leaf="true" version="9">
    <environmentId>apollo</environmentId>
    <hidden>false</hidden>
    <properties/>
    <references>java.util.UUID</references>
    <references>nabu.cms.payment.database.types.productSubscription</references>
    <references>java.util.Date</references>
    <references>nabu.cms.core.types.emodel.core.Node</references>
</node>
