<?xml version="1.0" encoding="UTF-8" standalone="yes"?>
<node artifactManager="be.nabu.eai.module.types.structure.StructureManager" created="2022-11-16T11:04:56.368+01:00" lastModified="2023-02-01T10:51:46.636+01:00" leaf="true" version="5">
    <environmentId>apollo</environmentId>
    <hidden>false</hidden>
    <locked>false</locked>
    <properties/>
    <references>nabu.cms.core.types.emodel.core.MasterDataEntry</references>
    <references>java.lang.String</references>
    <references>java.util.UUID</references>
    <references>nabu.cms.payment.database.types.paymentVatRegime</references>
</node>
